{
    "article_date": "today",
    "link_article": [],
    "article_subheading": null,
    "article_text": "Two Cal Poly students placed first in a technical paper competition held during the recent American Institute of Industrial Engineers Regional X student conference. Terry Boczek of Ventura and Grace Saiki of Stockton presented their paper, titled “The Design of a Fabrication Line to Manufacture a Cylindrical Part, \" at the conference held at the University of Texas, El Paso, in February. Both industrial engineering majors, they competed against students from six other universities, including Arizona State University and New Mexico State University. The paper was a fall quarter project for a course on facilities design. Before entering the paper at the regional conference, the students won an award at the local American Institute of Industrial Engineers Senior Chapter. The students' paper is now entered in competition for a national prize. The national rankings will be announced at the A HE national convention to be held late next ntonth in Detroit.\t< n Saiki, a junior, is the daughter of Mrs. Shoko Saiki of Stockton. She graduated from Edison High School in Stockton in June 1978. She has received three scholarships since attending Cal Poly. Boczek is a senior and the son of Mr. and Mrs. Louis Boczek of Ventura He is a 1977 graduate of Stj Bonventure High School in Ventura. He was chosen most outstanding undergraduate in industrial engineering during his sophomore year",
    "number_of_paragraphs": "7",
    "article_headline": "Students’ paper finishes first",
    "publication": "1981-45-103",
    "id": "48",
    "article_number": "13",
    "author": null,
    "page_number": "6",
    "link_image": []
}